{
  "system" : "SNOMED Clinical Terms",
  "code" : "181162001",
  "description" : "",
  "children" : [ {
    "system" : "http://snomed.info/sct",
    "code" : "181162001",
    "display" : "Entire cornea"
  }, {
    "system" : "http://snomed.info/sct",
    "code" : "368595003",
    "display" : "Entire cornea of left eye"
  }, {
    "system" : "http://snomed.info/sct",
    "code" : "368573002",
    "display" : "Entire cornea of right eye"
  }, {
    "system" : "http://snomed.info/sct",
    "code" : "368824002",
    "display" : "Entire transplanted cornea"
  } ]
}